toybox/__init__.py
toybox/human_play.py
toybox/toybox.py
toybox/interventions/__init__.py
toybox/interventions/amidar.py
toybox/interventions/base.py
toybox/interventions/breakout.py
toybox/interventions/gridworld.py
toybox/interventions/space_invaders.py
toybox_api-0.2.0.dist-info/METADATA
toybox_api-0.2.0.dist-info/WHEEL
toybox_api-0.2.0.dist-info/top_level.txt
toybox_api-0.2.0.dist-info/RECORD
